pixeler/__init__.py
pixeler/bot/__init__.py
pixeler/bot/bot.py
pixeler/bot/bot_status.py
pixeler/bot/bot_thread.py
pixeler/input/__init__.py
pixeler/input/keyboard.py
pixeler/input/mouse.py
pixeler/input/win32_window.py
pixeler/input/window.py
pixeler/math/__init__.py
pixeler/math/point.py
pixeler/math/random.py
pixeler/math/rectangle.py
pixeler/vision/__init__.py
pixeler/vision/color.py
pixeler/vision/ocr.py
pixeler/vision/oir.py
pixeler/vision/utils.py
pixeler-0.0.5.dist-info/METADATA
pixeler-0.0.5.dist-info/WHEEL
pixeler-0.0.5.dist-info/licenses/LICENSE
pixeler-0.0.5.dist-info/RECORD
